django_sharding/__init__.py
django_sharding/apps.py
django_sharding/management/__init__.py
django_sharding/management/commands/__init__.py
django_sharding/management/commands/create_postgres_sequences.py
django_sharding/management/commands/migrate.py
django_sharding/management/commands/showmigrations.py
django_sharding-4.0.0.dist-info/DESCRIPTION.rst
django_sharding-4.0.0.dist-info/METADATA
django_sharding-4.0.0.dist-info/RECORD
django_sharding-4.0.0.dist-info/WHEEL
django_sharding-4.0.0.dist-info/metadata.json
django_sharding-4.0.0.dist-info/top_level.txt
django_sharding_library/__init__.py
django_sharding_library/constants.py
django_sharding_library/decorators.py
django_sharding_library/exceptions.py
django_sharding_library/fields.py
django_sharding_library/id_generation_strategies.py
django_sharding_library/manager.py
django_sharding_library/models.py
django_sharding_library/router.py
django_sharding_library/routing_read_strategies.py
django_sharding_library/settings_helpers.py
django_sharding_library/sharding_functions.py
django_sharding_library/signals.py
django_sharding_library/sql.py
django_sharding_library/utils.py
django_sharding_library/management/__init__.py
django_sharding_library/management/commands/__init__.py
django_sharding_library/management/commands/create_postgres_sequences.py
django_sharding_library/management/commands/migrate.py
django_sharding_library/management/commands/showmigrations.py
