Metadata-Version: 2.0
Name: django-sharding
Version: 4.0.0
Summary: A sharding app to include in your project so that you can shard your data.
Home-page: https://github.com/JBKahn/django-sharding
Author: JBKahn
Author-email: josephbkahn@gmail.com
License: BSD
Keywords: django shard sharding library
Platform: UNKNOWN
Classifier: Framework :: Django
Classifier: Intended Audience :: Developers
Classifier: Natural Language :: English
Classifier: Programming Language :: Python :: 2.7
Classifier: Programming Language :: Python :: 3.4
Classifier: Programming Language :: Python :: 3.5
Classifier: Programming Language :: Python :: 3.6
Requires-Dist: dj-database-url (<1.0.0,>=0.4.1)
Requires-Dist: django (<3.0.0,>=1.8)
